{
  "variants": {
    "shape=single": { "model": "stardew:block/grass/spring/center" },
    "shape=center": { "model": "stardew:block/grass/spring/center" },
    "shape=top": { "model": "stardew:block/grass/spring/center" },
    "shape=bottom": { "model": "stardew:block/grass/spring/center" },
    "shape=left": { "model": "stardew:block/grass/spring/center" },
    "shape=right": { "model": "stardew:block/grass/spring/center" },
    "shape=top_left": { "model": "stardew:block/grass/spring/center" },
    "shape=top_right": { "model": "stardew:block/grass/spring/center" },
    "shape=bottom_left": { "model": "stardew:block/grass/spring/center" },
    "shape=bottom_right": { "model": "stardew:block/grass/spring/center" },
    "shape=horizontal_left": { "model": "stardew:block/grass/spring/center" },
    "shape=horizontal_mid": { "model": "stardew:block/grass/spring/center" },
    "shape=horizontal_right": { "model": "stardew:block/grass/spring/center" },
    "shape=vertical_top": { "model": "stardew:block/grass/spring/center" },
    "shape=vertical_mid": { "model": "stardew:block/grass/spring/center" },
    "shape=vertical_bottom": { "model": "stardew:block/grass/spring/center" },
    "shape=inner_top_left": { "model": "stardew:block/grass/spring/center" },
    "shape=inner_top_right": { "model": "stardew:block/grass/spring/center" },
    "shape=inner_bottom_left": { "model": "stardew:block/grass/spring/center" },
    "shape=inner_bottom_right": { "model": "stardew:block/grass/spring/center" }
  }
}